pyls_flake8/__init__.py
pyls_flake8/plugin.py
pyls_flake8-0.4.0.dist-info/LICENSE
pyls_flake8-0.4.0.dist-info/METADATA
pyls_flake8-0.4.0.dist-info/WHEEL
pyls_flake8-0.4.0.dist-info/entry_points.txt
pyls_flake8-0.4.0.dist-info/top_level.txt
pyls_flake8-0.4.0.dist-info/RECORD
