Metadata-Version: 2.1
Name: pyls-flake8
Version: 0.4.0
Summary: A Flake8 plugin for the Python Language Server
Home-page: https://github.com/emanspeaks/pyls-flake8
Author: Randy Eckman
Author-email: emanspeaks@gmail.com
Maintainer: Peter Justin
Maintainer-email: peter.justin@outlook.com
License: MIT
Platform: UNKNOWN
Classifier: Programming Language :: Python :: 3
Classifier: Programming Language :: Python :: 3.7
Classifier: License :: OSI Approved :: MIT License
Classifier: Operating System :: OS Independent
Requires-Dist: python-lsp-server
Requires-Dist: flake8 (>=3.6.0)
